{"nodes": [{"id": "c_users_v_mnmurugan_projects_eventkart_apps_api_src_lib_sentry_ts", "label": "sentry.ts", "file_type": "code", "source_file": "C:\\Users\\v-mnmurugan\\projects\\eventKart\\apps\\api\\src\\lib\\sentry.ts", "source_location": "L1"}, {"id": "lib_sentry_scrubobject", "label": "scrubObject()", "file_type": "code", "source_file": "C:\\Users\\v-mnmurugan\\projects\\eventKart\\apps\\api\\src\\lib\\sentry.ts", "source_location": "L40"}, {"id": "lib_sentry_scrubpii", "label": "scrubPii()", "file_type": "code", "source_file": "C:\\Users\\v-mnmurugan\\projects\\eventKart\\apps\\api\\src\\lib\\sentry.ts", "source_location": "L75"}, {"id": "lib_sentry_initsentry", "label": "initSentry()", "file_type": "code", "source_file": "C:\\Users\\v-mnmurugan\\projects\\eventKart\\apps\\api\\src\\lib\\sentry.ts", "source_location": "L145"}, {"id": "lib_sentry_issentryactive", "label": "isSentryActive()", "file_type": "code", "source_file": "C:\\Users\\v-mnmurugan\\projects\\eventKart\\apps\\api\\src\\lib\\sentry.ts", "source_location": "L165"}, {"id": "lib_sentry_setupfastifyerrorhandler", "label": "setupFastifyErrorHandler()", "file_type": "code", "source_file": "C:\\Users\\v-mnmurugan\\projects\\eventKart\\apps\\api\\src\\lib\\sentry.ts", "source_location": "L173"}, {"id": "lib_sentry_captureunexpectederror", "label": "captureUnexpectedError()", "file_type": "code", "source_file": "C:\\Users\\v-mnmurugan\\projects\\eventKart\\apps\\api\\src\\lib\\sentry.ts", "source_location": "L181"}, {"id": "lib_sentry_flushsentry", "label": "flushSentry()", "file_type": "code", "source_file": "C:\\Users\\v-mnmurugan\\projects\\eventKart\\apps\\api\\src\\lib\\sentry.ts", "source_location": "L195"}], "edges": [{"source": "c_users_v_mnmurugan_projects_eventkart_apps_api_src_lib_sentry_ts", "target": "node", "relation": "imports_from", "confidence": "EXTRACTED", "source_file": "C:\\Users\\v-mnmurugan\\projects\\eventKart\\apps\\api\\src\\lib\\sentry.ts", "source_location": "L1", "weight": 1.0}, {"source": "c_users_v_mnmurugan_projects_eventkart_apps_api_src_lib_sentry_ts", "target": "node", "relation": "imports_from", "confidence": "EXTRACTED", "source_file": "C:\\Users\\v-mnmurugan\\projects\\eventKart\\apps\\api\\src\\lib\\sentry.ts", "source_location": "L2", "weight": 1.0}, {"source": "c_users_v_mnmurugan_projects_eventkart_apps_api_src_lib_sentry_ts", "target": "fastify", "relation": "imports_from", "confidence": "EXTRACTED", "source_file": "C:\\Users\\v-mnmurugan\\projects\\eventKart\\apps\\api\\src\\lib\\sentry.ts", "source_location": "L3", "weight": 1.0}, {"source": "c_users_v_mnmurugan_projects_eventkart_apps_api_src_lib_sentry_ts", "target": "c_users_v_mnmurugan_projects_eventkart_apps_api_src_lib_config_ts", "relation": "imports_from", "confidence": "EXTRACTED", "source_file": "C:\\Users\\v-mnmurugan\\projects\\eventKart\\apps\\api\\src\\lib\\sentry.ts", "source_location": "L4", "weight": 1.0}, {"source": "c_users_v_mnmurugan_projects_eventkart_apps_api_src_lib_sentry_ts", "target": "lib_sentry_scrubobject", "relation": "contains", "confidence": "EXTRACTED", "source_file": "C:\\Users\\v-mnmurugan\\projects\\eventKart\\apps\\api\\src\\lib\\sentry.ts", "source_location": "L40", "weight": 1.0}, {"source": "c_users_v_mnmurugan_projects_eventkart_apps_api_src_lib_sentry_ts", "target": "lib_sentry_scrubpii", "relation": "contains", "confidence": "EXTRACTED", "source_file": "C:\\Users\\v-mnmurugan\\projects\\eventKart\\apps\\api\\src\\lib\\sentry.ts", "source_location": "L75", "weight": 1.0}, {"source": "c_users_v_mnmurugan_projects_eventkart_apps_api_src_lib_sentry_ts", "target": "lib_sentry_initsentry", "relation": "contains", "confidence": "EXTRACTED", "source_file": "C:\\Users\\v-mnmurugan\\projects\\eventKart\\apps\\api\\src\\lib\\sentry.ts", "source_location": "L145", "weight": 1.0}, {"source": "c_users_v_mnmurugan_projects_eventkart_apps_api_src_lib_sentry_ts", "target": "lib_sentry_issentryactive", "relation": "contains", "confidence": "EXTRACTED", "source_file": "C:\\Users\\v-mnmurugan\\projects\\eventKart\\apps\\api\\src\\lib\\sentry.ts", "source_location": "L165", "weight": 1.0}, {"source": "c_users_v_mnmurugan_projects_eventkart_apps_api_src_lib_sentry_ts", "target": "lib_sentry_setupfastifyerrorhandler", "relation": "contains", "confidence": "EXTRACTED", "source_file": "C:\\Users\\v-mnmurugan\\projects\\eventKart\\apps\\api\\src\\lib\\sentry.ts", "source_location": "L173", "weight": 1.0}, {"source": "c_users_v_mnmurugan_projects_eventkart_apps_api_src_lib_sentry_ts", "target": "lib_sentry_captureunexpectederror", "relation": "contains", "confidence": "EXTRACTED", "source_file": "C:\\Users\\v-mnmurugan\\projects\\eventKart\\apps\\api\\src\\lib\\sentry.ts", "source_location": "L181", "weight": 1.0}, {"source": "c_users_v_mnmurugan_projects_eventkart_apps_api_src_lib_sentry_ts", "target": "lib_sentry_flushsentry", "relation": "contains", "confidence": "EXTRACTED", "source_file": "C:\\Users\\v-mnmurugan\\projects\\eventKart\\apps\\api\\src\\lib\\sentry.ts", "source_location": "L195", "weight": 1.0}, {"source": "lib_sentry_scrubpii", "target": "lib_sentry_scrubobject", "relation": "calls", "confidence": "EXTRACTED", "source_file": "C:\\Users\\v-mnmurugan\\projects\\eventKart\\apps\\api\\src\\lib\\sentry.ts", "source_location": "L105", "weight": 1.0}], "raw_calls": [{"caller_nid": "lib_sentry_scrubobject", "callee": "replace", "is_member_call": true, "source_file": "C:\\Users\\v-mnmurugan\\projects\\eventKart\\apps\\api\\src\\lib\\sentry.ts", "source_location": "L46"}, {"caller_nid": "lib_sentry_scrubobject", "callee": "replace", "is_member_call": true, "source_file": "C:\\Users\\v-mnmurugan\\projects\\eventKart\\apps\\api\\src\\lib\\sentry.ts", "source_location": "L46"}, {"caller_nid": "lib_sentry_scrubobject", "callee": "isArray", "is_member_call": true, "source_file": "C:\\Users\\v-mnmurugan\\projects\\eventKart\\apps\\api\\src\\lib\\sentry.ts", "source_location": "L51"}, {"caller_nid": "lib_sentry_scrubobject", "callee": "map", "is_member_call": true, "source_file": "C:\\Users\\v-mnmurugan\\projects\\eventKart\\apps\\api\\src\\lib\\sentry.ts", "source_location": "L52"}, {"caller_nid": "lib_sentry_scrubobject", "callee": "entries", "is_member_call": true, "source_file": "C:\\Users\\v-mnmurugan\\projects\\eventKart\\apps\\api\\src\\lib\\sentry.ts", "source_location": "L57"}, {"caller_nid": "lib_sentry_scrubobject", "callee": "has", "is_member_call": true, "source_file": "C:\\Users\\v-mnmurugan\\projects\\eventKart\\apps\\api\\src\\lib\\sentry.ts", "source_location": "L58"}, {"caller_nid": "lib_sentry_scrubobject", "callee": "toLowerCase", "is_member_call": true, "source_file": "C:\\Users\\v-mnmurugan\\projects\\eventKart\\apps\\api\\src\\lib\\sentry.ts", "source_location": "L58"}, {"caller_nid": "lib_sentry_scrubpii", "callee": "replace", "is_member_call": true, "source_file": "C:\\Users\\v-mnmurugan\\projects\\eventKart\\apps\\api\\src\\lib\\sentry.ts", "source_location": "L78"}, {"caller_nid": "lib_sentry_scrubpii", "callee": "replace", "is_member_call": true, "source_file": "C:\\Users\\v-mnmurugan\\projects\\eventKart\\apps\\api\\src\\lib\\sentry.ts", "source_location": "L78"}, {"caller_nid": "lib_sentry_scrubpii", "callee": "replace", "is_member_call": true, "source_file": "C:\\Users\\v-mnmurugan\\projects\\eventKart\\apps\\api\\src\\lib\\sentry.ts", "source_location": "L87"}, {"caller_nid": "lib_sentry_scrubpii", "callee": "replace", "is_member_call": true, "source_file": "C:\\Users\\v-mnmurugan\\projects\\eventKart\\apps\\api\\src\\lib\\sentry.ts", "source_location": "L87"}, {"caller_nid": "lib_sentry_scrubpii", "callee": "replace", "is_member_call": true, "source_file": "C:\\Users\\v-mnmurugan\\projects\\eventKart\\apps\\api\\src\\lib\\sentry.ts", "source_location": "L125"}, {"caller_nid": "lib_sentry_scrubpii", "callee": "replace", "is_member_call": true, "source_file": "C:\\Users\\v-mnmurugan\\projects\\eventKart\\apps\\api\\src\\lib\\sentry.ts", "source_location": "L125"}, {"caller_nid": "lib_sentry_initsentry", "callee": "init", "is_member_call": true, "source_file": "C:\\Users\\v-mnmurugan\\projects\\eventKart\\apps\\api\\src\\lib\\sentry.ts", "source_location": "L150"}, {"caller_nid": "lib_sentry_initsentry", "callee": "fastifyIntegration", "is_member_call": true, "source_file": "C:\\Users\\v-mnmurugan\\projects\\eventKart\\apps\\api\\src\\lib\\sentry.ts", "source_location": "L156"}, {"caller_nid": "lib_sentry_captureunexpectederror", "callee": "captureException", "is_member_call": true, "source_file": "C:\\Users\\v-mnmurugan\\projects\\eventKart\\apps\\api\\src\\lib\\sentry.ts", "source_location": "L189"}, {"caller_nid": "lib_sentry_flushsentry", "callee": "close", "is_member_call": true, "source_file": "C:\\Users\\v-mnmurugan\\projects\\eventKart\\apps\\api\\src\\lib\\sentry.ts", "source_location": "L200"}]}