{"nodes": [{"id": "c_users_v_mnmurugan_projects_eventkart_apps_web_src_features_auth_components_phone_input_tsx", "label": "phone-input.tsx", "file_type": "code", "source_file": "C:\\Users\\v-mnmurugan\\projects\\eventKart\\apps\\web\\src\\features\\auth\\components\\phone-input.tsx", "source_location": "L1"}, {"id": "components_phone_input_phoneinput", "label": "PhoneInput()", "file_type": "code", "source_file": "C:\\Users\\v-mnmurugan\\projects\\eventKart\\apps\\web\\src\\features\\auth\\components\\phone-input.tsx", "source_location": "L12"}], "edges": [{"source": "c_users_v_mnmurugan_projects_eventkart_apps_web_src_features_auth_components_phone_input_tsx", "target": "input", "relation": "imports_from", "confidence": "EXTRACTED", "source_file": "C:\\Users\\v-mnmurugan\\projects\\eventKart\\apps\\web\\src\\features\\auth\\components\\phone-input.tsx", "source_location": "L1", "weight": 1.0}, {"source": "c_users_v_mnmurugan_projects_eventkart_apps_web_src_features_auth_components_phone_input_tsx", "target": "react", "relation": "imports_from", "confidence": "EXTRACTED", "source_file": "C:\\Users\\v-mnmurugan\\projects\\eventKart\\apps\\web\\src\\features\\auth\\components\\phone-input.tsx", "source_location": "L2", "weight": 1.0}, {"source": "c_users_v_mnmurugan_projects_eventkart_apps_web_src_features_auth_components_phone_input_tsx", "target": "components_phone_input_phoneinput", "relation": "contains", "confidence": "EXTRACTED", "source_file": "C:\\Users\\v-mnmurugan\\projects\\eventKart\\apps\\web\\src\\features\\auth\\components\\phone-input.tsx", "source_location": "L12", "weight": 1.0}], "raw_calls": [{"caller_nid": "components_phone_input_phoneinput", "callee": "useId", "is_member_call": false, "source_file": "C:\\Users\\v-mnmurugan\\projects\\eventKart\\apps\\web\\src\\features\\auth\\components\\phone-input.tsx", "source_location": "L19"}]}